[{"name": "Attard", "country_iso2": "MT", "state": "Attard", "is_capital": true, "latitude": 35.8928, "longitude": 14.4383, "population": 10930}, {"name": "Balzan", "country_iso2": "MT", "state": "Balzan", "is_capital": true, "latitude": 35.8981, "longitude": 14.4533, "population": 3958}, {"name": "Birkirkara", "country_iso2": "MT", "state": "Birkirkara", "is_capital": true, "latitude": 35.8967, "longitude": 14.4625, "population": 24356}, {"name": "Birżebbuġa", "country_iso2": "MT", "state": "Birżebbuġa", "is_capital": true, "latitude": 35.8256, "longitude": 14.5281, "population": 9736}, {"name": "Cospicua", "country_iso2": "MT", "state": "Bormla", "is_capital": true, "latitude": 35.8822, "longitude": 14.5222, "population": 5395}, {"name": "Dingli", "country_iso2": "MT", "state": "Dingli", "is_capital": true, "latitude": 35.8603, "longitude": 14.3814, "population": 3608}, {"name": "Fgura", "country_iso2": "MT", "state": "Fgura", "is_capital": true, "latitude": 35.8725, "longitude": 14.5228, "population": 11670}, {"name": "Floriana", "country_iso2": "MT", "state": "Floriana", "is_capital": true, "latitude": 35.8933, "longitude": 14.5058, "population": 2205}, {"name": "Fontana", "country_iso2": "MT", "state": "Fontana", "is_capital": true, "latitude": 36.0364, "longitude": 14.2422, "population": 922}, {"name": "Gudja", "country_iso2": "MT", "state": "Gudja", "is_capital": true, "latitude": 35.8483, "longitude": 14.5025, "population": 2997}, {"name": "Għajnsielem", "country_iso2": "MT", "state": "Għajnsielem", "is_capital": true, "latitude": 36.0269, "longitude": 14.2903, "population": 3200}, {"name": "Għarb", "country_iso2": "MT", "state": "Għarb", "is_capital": true, "latitude": 36.0611, "longitude": 14.2092, "population": 1539}, {"name": "Għargħur", "country_iso2": "MT", "state": "Għargħur", "is_capital": true, "latitude": 35.9241, "longitude": 14.4534, "population": 2768}, {"name": "Għasri", "country_iso2": "MT", "state": "Għasri", "is_capital": true, "latitude": 36.0583, "longitude": 14.2278, "population": 424}, {"name": "Għaxaq", "country_iso2": "MT", "state": "Għaxaq", "is_capital": true, "latitude": 35.8483, "longitude": 14.5172, "population": 4722}, {"name": "Gżira", "country_iso2": "MT", "state": "Gżira", "is_capital": true, "latitude": 35.905, "longitude": 14.4944, "population": 8029}, {"name": "Iklin", "country_iso2": "MT", "state": "Iklin", "is_capital": true, "latitude": 35.9042, "longitude": 14.4544, "population": 3130}, {"name": "Imdina", "country_iso2": "MT", "state": "Imdina", "is_capital": true, "latitude": 35.8858, "longitude": 14.4031, "population": 292}, {"name": "Imqabba", "country_iso2": "MT", "state": "Imqabba", "is_capital": true, "latitude": 35.8442, "longitude": 14.4669, "population": 3315}, {"name": "Imsida", "country_iso2": "MT", "state": "Imsida", "is_capital": true, "latitude": 35.8978, "longitude": 14.4894, "population": 8545}, {"name": "Imtarfa", "country_iso2": "MT", "state": "Imtarfa", "is_capital": true, "latitude": 35.8908, "longitude": 14.3969, "population": 2572}, {"name": "Imġarr", "country_iso2": "MT", "state": "Imġarr", "is_capital": true, "latitude": 35.9197, "longitude": 14.3664, "population": 3629}, {"name": "Kalkara", "country_iso2": "MT", "state": "Kalkara", "is_capital": true, "latitude": 35.8892, "longitude": 14.5294, "population": 3014}, {"name": "Kerċem", "country_iso2": "MT", "state": "Kerċem", "is_capital": true, "latitude": 36.0406, "longitude": 14.2297, "population": 1938}, {"name": "Kirkop", "country_iso2": "MT", "state": "Kirkop", "is_capital": true, "latitude": 35.8419, "longitude": 14.485, "population": 2191}, {"name": "Lija", "country_iso2": "MT", "state": "Lija", "is_capital": true, "latitude": 35.9014, "longitude": 14.4472, "population": 3070}, {"name": "Luqa", "country_iso2": "MT", "state": "Luqa", "is_capital": true, "latitude": 35.8597, "longitude": 14.4892, "population": 5945}, {"name": "Marsa", "country_iso2": "MT", "state": "Marsa", "is_capital": true, "latitude": 35.8833, "longitude": 14.4947, "population": 4401}, {"name": "Marsaskala", "country_iso2": "MT", "state": "Marsaskala", "is_capital": true, "latitude": 35.8625, "longitude": 14.5675, "population": 15579}, {"name": "Marsaxlokk", "country_iso2": "MT", "state": "Marsaxlokk", "is_capital": true, "latitude": 35.8417, "longitude": 14.5447, "population": 3534}, {"name": "Mellieħa", "country_iso2": "MT", "state": "Mellieħa", "is_capital": true, "latitude": 35.9564, "longitude": 14.3664, "population": 10087}, {"name": "Mosta", "country_iso2": "MT", "state": "Mosta", "is_capital": true, "latitude": 35.9097, "longitude": 14.4261, "population": 20241}, {"name": "Munxar", "country_iso2": "MT", "state": "Munxar", "is_capital": true, "latitude": 36.0303, "longitude": 14.2353, "population": 1454}, {"name": "Nadur", "country_iso2": "MT", "state": "Nadur", "is_capital": true, "latitude": 36.0381, "longitude": 14.295, "population": 4509}, {"name": "Naxxar", "country_iso2": "MT", "state": "Naxxar", "is_capital": true, "latitude": 35.915, "longitude": 14.4447, "population": 14890}, {"name": "Paola", "country_iso2": "MT", "state": "Paola", "is_capital": true, "latitude": 35.8728, "longitude": 14.5075, "population": 8706}, {"name": "Pembroke", "country_iso2": "MT", "state": "Pembroke", "is_capital": true, "latitude": 35.9264, "longitude": 14.4808, "population": 3645}, {"name": "Pietà", "country_iso2": "MT", "state": "Pietà", "is_capital": true, "latitude": 35.8931, "longitude": 14.4936, "population": 4020}, {"name": "Qala", "country_iso2": "MT", "state": "Qala", "is_capital": true, "latitude": 36.0353, "longitude": 14.3103, "population": 2284}, {"name": "Qormi", "country_iso2": "MT", "state": "Qormi", "is_capital": true, "latitude": 35.8794, "longitude": 14.4722, "population": 93897}, {"name": "Qrendi", "country_iso2": "MT", "state": "Qrendi", "is_capital": true, "latitude": 35.8342, "longitude": 14.4589, "population": 2752}, {"name": "Rabat", "country_iso2": "MT", "state": "Rabat", "is_capital": true, "latitude": 35.8817, "longitude": 14.3989, "population": 11497}, {"name": "Safi", "country_iso2": "MT", "state": "Safi", "is_capital": true, "latitude": 35.8333, "longitude": 14.485, "population": 2126}, {"name": "Saint Paul’s Bay", "country_iso2": "MT", "state": "San Pawl il-Baħar", "is_capital": true, "latitude": 35.9483, "longitude": 14.4017, "population": 32042}, {"name": "San Lawrenz", "country_iso2": "MT", "state": "San Lawrenz", "is_capital": true, "latitude": 36.055, "longitude": 14.2042, "population": 748}, {"name": "San Ġiljan", "country_iso2": "MT", "state": "San Ġiljan", "is_capital": true, "latitude": 35.9186, "longitude": 14.49, "population": 13792}, {"name": "San Ġwann", "country_iso2": "MT", "state": "San Ġwann", "is_capital": true, "latitude": 35.9094, "longitude": 14.4786, "population": 14720}, {"name": "Sannat", "country_iso2": "MT", "state": "Sannat", "is_capital": true, "latitude": 36.0244, "longitude": 14.2458, "population": 2117}, {"name": "Santa Luċija", "country_iso2": "MT", "state": "Santa Luċija", "is_capital": true, "latitude": 36.0431, "longitude": 14.2172, "population": null}, {"name": "Santa Venera", "country_iso2": "MT", "state": "Santa Venera", "is_capital": true, "latitude": 35.8897, "longitude": 14.4778, "population": 6932}, {"name": "Senglea", "country_iso2": "MT", "state": "Isla", "is_capital": true, "latitude": 35.8878, "longitude": 14.5169, "population": 2784}, {"name": "Siġġiewi", "country_iso2": "MT", "state": "Siġġiewi", "is_capital": true, "latitude": 35.8542, "longitude": 14.4383, "population": 8721}, {"name": "Sliema", "country_iso2": "MT", "state": "Sliema", "is_capital": true, "latitude": 35.9122, "longitude": 14.5042, "population": 22591}, {"name": "Swieqi", "country_iso2": "MT", "state": "Swieqi", "is_capital": true, "latitude": 35.9208, "longitude": 14.48, "population": 10064}, {"name": "Tarxien", "country_iso2": "MT", "state": "Tarxien", "is_capital": true, "latitude": 35.8658, "longitude": 14.5119, "population": 8583}, {"name": "Ta’ Xbiex", "country_iso2": "MT", "state": "Ta’ Xbiex", "is_capital": true, "latitude": 35.8992, "longitude": 14.4981, "population": 1804}, {"name": "Valletta", "country_iso2": "MT", "state": "Valletta", "is_capital": true, "latitude": 35.8983, "longitude": 14.5125, "population": 480134}, {"name": "Victoria", "country_iso2": "MT", "state": "Rabat (Ghawdex)", "is_capital": true, "latitude": 36.0436, "longitude": 14.2431, "population": 6901}, {"name": "Vittoriosa", "country_iso2": "MT", "state": "Birgu", "is_capital": true, "latitude": 35.8881, "longitude": 14.5225, "population": 2629}, {"name": "Xagħra", "country_iso2": "MT", "state": "Xagħra", "is_capital": true, "latitude": 36.0503, "longitude": 14.2675, "population": 4886}, {"name": "Xewkija", "country_iso2": "MT", "state": "Xewkija", "is_capital": true, "latitude": 36.0331, "longitude": 14.2583, "population": 3300}, {"name": "Xgħajra", "country_iso2": "MT", "state": "Xgħajra", "is_capital": true, "latitude": 35.8864, "longitude": 14.5472, "population": 1732}, {"name": "Ħamrun", "country_iso2": "MT", "state": "Ħamrun", "is_capital": true, "latitude": 35.8861, "longitude": 14.4894, "population": 9743}, {"name": "Żabbar", "country_iso2": "MT", "state": "Żabbar", "is_capital": true, "latitude": 35.8772, "longitude": 14.5381, "population": 15404}, {"name": "Żebbuġ", "country_iso2": "MT", "state": "Żebbuġ", "is_capital": true, "latitude": 35.8731, "longitude": 14.4419, "population": 11903}, {"name": "Żebbuġ", "country_iso2": "MT", "state": "Żebbuġ (Ghawdex)", "is_capital": true, "latitude": 36.0708, "longitude": 14.2369, "population": 2956}, {"name": "Żejtun", "country_iso2": "MT", "state": "Żejtun", "is_capital": true, "latitude": 35.8556, "longitude": 14.5333, "population": 11508}, {"name": "Żurrieq", "country_iso2": "MT", "state": "Żurrieq", "is_capital": true, "latitude": 35.8292, "longitude": 14.4758, "population": 10823}]